basic_open_agent_tools/__init__.py
basic_open_agent_tools/_logging.py
basic_open_agent_tools/confirmation.py
basic_open_agent_tools/decorators.py
basic_open_agent_tools/exceptions.py
basic_open_agent_tools/helpers.py
basic_open_agent_tools/types.py
basic_open_agent_tools/archive/__init__.py
basic_open_agent_tools/archive/compression.py
basic_open_agent_tools/archive/formats.py
basic_open_agent_tools/color/__init__.py
basic_open_agent_tools/color/analysis.py
basic_open_agent_tools/color/conversion.py
basic_open_agent_tools/color/generation.py
basic_open_agent_tools/crypto/__init__.py
basic_open_agent_tools/crypto/encoding.py
basic_open_agent_tools/crypto/generation.py
basic_open_agent_tools/crypto/hashing.py
basic_open_agent_tools/data/__init__.py
basic_open_agent_tools/data/config_processing.py
basic_open_agent_tools/data/csv_tools.py
basic_open_agent_tools/data/json_tools.py
basic_open_agent_tools/data/validation.py
basic_open_agent_tools/datetime/__init__.py
basic_open_agent_tools/datetime/business.py
basic_open_agent_tools/datetime/formatting.py
basic_open_agent_tools/datetime/info.py
basic_open_agent_tools/datetime/operations.py
basic_open_agent_tools/datetime/ranges.py
basic_open_agent_tools/datetime/timezone.py
basic_open_agent_tools/datetime/validation.py
basic_open_agent_tools/diagrams/__init__.py
basic_open_agent_tools/diagrams/mermaid.py
basic_open_agent_tools/diagrams/plantuml.py
basic_open_agent_tools/excel/__init__.py
basic_open_agent_tools/excel/formatting.py
basic_open_agent_tools/excel/reading.py
basic_open_agent_tools/excel/writing.py
basic_open_agent_tools/file_system/__init__.py
basic_open_agent_tools/file_system/editor.py
basic_open_agent_tools/file_system/info.py
basic_open_agent_tools/file_system/operations.py
basic_open_agent_tools/file_system/tree.py
basic_open_agent_tools/file_system/validation.py
basic_open_agent_tools/html/__init__.py
basic_open_agent_tools/html/generation.py
basic_open_agent_tools/html/parsing.py
basic_open_agent_tools-1.2.1.dist-info/licenses/LICENSE
basic_open_agent_tools-1.2.1.dist-info/METADATA
basic_open_agent_tools-1.2.1.dist-info/WHEEL
basic_open_agent_tools-1.2.1.dist-info/top_level.txt
basic_open_agent_tools-1.2.1.dist-info/RECORD
