Metadata-Version: 2.4
Name: basic-open-agent-tools
Version: 1.2.1
Summary: An open foundational toolkit providing essential components for building AI agents with minimal dependencies for local (non-HTTP/API) actions.
Author-email: Open Agent Tools <unseriousai@gmail.com>
Project-URL: Homepage, https://github.com/open-agent-tools/basic-open-agent-tools
Project-URL: Documentation, https://github.com/open-agent-tools/basic-open-agent-tools#readme
Project-URL: Repository, https://github.com/open-agent-tools/basic-open-agent-tools
Project-URL: Issues, https://github.com/open-agent-tools/basic-open-agent-tools/issues
Keywords: ai,agents,toolkit,automation,local-tools
Classifier: Development Status :: 3 - Alpha
Classifier: Environment :: Console
Classifier: Intended Audience :: Developers
Classifier: License :: OSI Approved :: MIT License
Classifier: Natural Language :: English
Classifier: Operating System :: OS Independent
Classifier: Programming Language :: Python :: 3
Classifier: Programming Language :: Python :: 3.9
Classifier: Programming Language :: Python :: 3.10
Classifier: Programming Language :: Python :: 3.11
Classifier: Programming Language :: Python :: 3.12
Classifier: Topic :: Communications :: Chat
Classifier: Topic :: Scientific/Engineering :: Artificial Intelligence
Classifier: Topic :: Software Development :: Libraries :: Application Frameworks
Classifier: Topic :: Software Development :: Libraries :: Python Modules
Classifier: Typing :: Typed
Requires-Python: >=3.9
License-File: LICENSE
Provides-Extra: system
Requires-Dist: psutil>=5.9.0; extra == "system"
Provides-Extra: pdf
Requires-Dist: PyPDF2>=3.0.0; extra == "pdf"
Requires-Dist: reportlab>=4.0.0; extra == "pdf"
Provides-Extra: xml
Requires-Dist: lxml>=4.9.0; extra == "xml"
Requires-Dist: defusedxml>=0.7.1; extra == "xml"
Provides-Extra: word
Requires-Dist: python-docx>=0.8.11; extra == "word"
Provides-Extra: excel
Requires-Dist: openpyxl>=3.1.0; extra == "excel"
Provides-Extra: powerpoint
Requires-Dist: python-pptx>=0.6.21; extra == "powerpoint"
Provides-Extra: image
Requires-Dist: Pillow>=10.0.0; extra == "image"
Provides-Extra: data
Requires-Dist: pyyaml>=6.0.0; extra == "data"
Requires-Dist: tomli>=2.0.0; python_version < "3.11" and extra == "data"
Requires-Dist: tomli-w>=1.0.0; extra == "data"
Provides-Extra: all
Requires-Dist: psutil>=5.9.0; extra == "all"
Requires-Dist: PyPDF2>=3.0.0; extra == "all"
Requires-Dist: reportlab>=4.0.0; extra == "all"
Requires-Dist: lxml>=4.9.0; extra == "all"
Requires-Dist: defusedxml>=0.7.1; extra == "all"
Requires-Dist: python-docx>=0.8.11; extra == "all"
Requires-Dist: openpyxl>=3.1.0; extra == "all"
Requires-Dist: python-pptx>=0.6.21; extra == "all"
Requires-Dist: Pillow>=10.0.0; extra == "all"
Requires-Dist: pyyaml>=6.0.0; extra == "all"
Requires-Dist: tomli>=2.0.0; python_version < "3.11" and extra == "all"
Requires-Dist: tomli-w>=1.0.0; extra == "all"
Provides-Extra: strands
Requires-Dist: strands>=0.1.0; extra == "strands"
Requires-Dist: anthropic>=0.25.0; extra == "strands"
Requires-Dist: python-dotenv>=1.0.0; extra == "strands"
Provides-Extra: dev
Requires-Dist: pytest>=7.0.0; extra == "dev"
Requires-Dist: pytest-cov>=4.0.0; extra == "dev"
Requires-Dist: pytest-asyncio>=0.21.0; extra == "dev"
Requires-Dist: ruff>=0.1.0; extra == "dev"
Requires-Dist: mypy>=1.0.0; extra == "dev"
Requires-Dist: pre-commit>=3.0.0; extra == "dev"
Requires-Dist: freezegun>=1.2.0; extra == "dev"
Requires-Dist: tomli>=2.0.0; python_version < "3.11" and extra == "dev"
Requires-Dist: tomli-w>=1.0.0; extra == "dev"
Requires-Dist: pyyaml>=6.0.0; extra == "dev"
Requires-Dist: google-adk>=0.1.0; extra == "dev"
Requires-Dist: psutil>=5.9.0; extra == "dev"
Requires-Dist: PyPDF2>=3.0.0; extra == "dev"
Requires-Dist: reportlab>=4.0.0; extra == "dev"
Requires-Dist: lxml>=4.9.0; extra == "dev"
Requires-Dist: defusedxml>=0.7.1; extra == "dev"
Requires-Dist: python-docx>=0.8.11; extra == "dev"
Requires-Dist: openpyxl>=3.1.0; extra == "dev"
Requires-Dist: python-pptx>=0.6.21; extra == "dev"
Requires-Dist: Pillow>=10.0.0; extra == "dev"
Requires-Dist: strands>=0.1.0; extra == "dev"
Requires-Dist: anthropic>=0.25.0; extra == "dev"
Requires-Dist: python-dotenv>=1.0.0; extra == "dev"
Provides-Extra: test
Requires-Dist: pytest>=7.0.0; extra == "test"
Requires-Dist: pytest-cov>=4.0.0; extra == "test"
Requires-Dist: pytest-asyncio>=0.21.0; extra == "test"
Requires-Dist: freezegun>=1.2.0; extra == "test"
Requires-Dist: tomli>=2.0.0; python_version < "3.11" and extra == "test"
Requires-Dist: tomli-w>=1.0.0; extra == "test"
Requires-Dist: pyyaml>=6.0.0; extra == "test"
Requires-Dist: google-adk>=0.1.0; extra == "test"
Requires-Dist: psutil>=5.9.0; extra == "test"
Requires-Dist: PyPDF2>=3.0.0; extra == "test"
Requires-Dist: reportlab>=4.0.0; extra == "test"
Requires-Dist: lxml>=4.9.0; extra == "test"
Requires-Dist: defusedxml>=0.7.1; extra == "test"
Requires-Dist: python-docx>=0.8.11; extra == "test"
Requires-Dist: openpyxl>=3.1.0; extra == "test"
Requires-Dist: python-pptx>=0.6.21; extra == "test"
Requires-Dist: Pillow>=10.0.0; extra == "test"
Dynamic: license-file
